<?xml version='1.0' encoding='EUC-JP'?>
<jisyo>
  <!-- people & organizations -->

  <ca>
    <word>A.B.C-Z</word>
    <annotation>音楽グループ</annotation>
  </ca>

  <ca>
    <word>ACSiON</word>
    <annotation>[企業名]</annotation>
  </ca>

  <ca>
    <word>ADsFactory</word>
    <annotation>[企業名]</annotation>
  </ca>

  <ca>
    <word>pixiv</word>
    <annotation>[企業名]</annotation>
    <!-- 商標登録5271270 -->
  </ca>

  <!-- pixiv https://www.pixiv.co.jp/service/ -->
  <ca>
    <word>BOOTH</word>
    <annotation>https://booth.pm/</annotation>
  </ca>

  <ca>
    <word>ImageFlux</word>
    <annotation><annotation>
  </ca>

  <ca>
    <word>pixivFACTORY</word>
  </ca>

  <ca>
    <word>pixivFANBOX</word>
  </ca>

  <ca>
    <word>pixivision</word>
  </ca>

  <ca>
    <word>pixiv Sketch</word>
  </ca>

  <ca>
    <word>pixiv WAEN GALLERY</word>
  </ca>

  <ca>
    <word>sensei</word>
    <annotation>https://sensei.pixiv.net/<annotation>
  </ca>

  <ca>
    <word>VRoid Hub</word>
  </ca>

  <ca>
    <word>VRoid Studio</word>
  </ca>
  <!-- / pixiv -->

</jisyo>
